iometer/__init__.py
iometer/client.py
iometer/exceptions.py
iometer/reading.py
iometer/status.py
iometer-0.2.0.dist-info/LICENSE
iometer-0.2.0.dist-info/METADATA
iometer-0.2.0.dist-info/WHEEL
iometer-0.2.0.dist-info/RECORD
