Metadata-Version: 2.3
Name: iometer
Version: 0.2.0
Summary: Asynchronous Python client for IOmeter
Home-page: https://iometer.de/
License: MIT
Keywords: IOmeter,smart meter,energy,automation
Author: jukrebs
Author-email: justus@iometer.de
Requires-Python: >=3.10,<4.0
Classifier: License :: OSI Approved :: MIT License
Classifier: Operating System :: OS Independent
Classifier: Programming Language :: Python :: 3
Classifier: Programming Language :: Python :: 3.10
Classifier: Programming Language :: Python :: 3.11
Classifier: Programming Language :: Python :: 3.12
Classifier: Programming Language :: Python :: 3.13
Requires-Dist: aiohttp (>=3.0.0,<4.0.0)
Requires-Dist: yarl (>=1.6.0)
Project-URL: Documentation, https://github.com/iometer-gmbh/iometer.py/blob/main/docs/index.md
Project-URL: Repository, https://github.com/iometer-gmbh/iometer.py
